pypromises/__init__.py
pypromises/fire_and_forget.py
pypromises/promise.py
pypromises-0.0.4.dist-info/METADATA
pypromises-0.0.4.dist-info/WHEEL
pypromises-0.0.4.dist-info/licenses/LICENSE
pypromises-0.0.4.dist-info/RECORD
