Metadata-Version: 2.1
Name: pypromises
Version: 0.0.4
Project-URL: Homepage, https://github.com/RizwanAmjad/py-promises
Project-URL: Bug Tracker, https://github.com/RizwanAmjad/py-promises/issues
Author-email: Rizwan Amjad <rizwanamjadnov@gmail.com>
License-File: LICENSE
Classifier: License :: OSI Approved :: MIT License
Classifier: Operating System :: OS Independent
Classifier: Programming Language :: Python :: 3
Requires-Python: >=3.7
